{"index.md":"ilU0zeU_","readme.md":"BSsjicTQ","团队_index.md":"maN66JZU","地图_index.md":"CTflS5qe","地图_东胜神洲_index.md":"DdUVIT7V","地图_东胜神洲_云川.md":"D6NAU0N8","地图_东胜神洲_电.md":"Vz1siNA_","地图_东胜神洲_雨.md":"BlQDQ9Pc","地图_东胜神洲_雷.md":"CnM7nT80","地图_东胜神洲_风.md":"D608wWrr","地图_六欲魔天_1.md":"DXHjTEb0","地图_六欲魔天_2.md":"CLVf9Mwu","地图_六欲魔天_3.md":"BLlroOb7","地图_六欲魔天_4.md":"DcnaxJt8","地图_六欲魔天_5.md":"ox10lBZQ","地图_六欲魔天_6.md":"DoBKDl2o","地图_六欲魔天_index.md":"tnMHzpFj","地图_北俱芦洲_index.md":"BKQcEHEs","地图_北俱芦洲_天气.md":"DY3_MybE","地图_北俱芦洲_时间.md":"CffEZPzA","地图_北俱芦洲_星域.md":"DJ25Akvx","地图_北俱芦洲_空间.md":"BpTT8B_w","地图_南瞻部洲_index.md":"BNFesbeG","地图_南瞻部洲_冥海.md":"-NLz7pS9","地图_南瞻部洲_土.md":"CdrZNVxA","地图_南瞻部洲_木.md":"CAlTQKLh","地图_南瞻部洲_水.md":"D2tSW2ZT","地图_南瞻部洲_火.md":"BTPvanEp","地图_南瞻部洲_金.md":"C-kafF73","地图_幽冥血海_index.md":"CG-GTm4J","地图_幽冥血海_伽岚.md":"CiuLY65U","地图_幽冥血海_无冥.md":"CL1WpJE1","地图_幽冥血海_洛湮.md":"C4rg-Lky","地图_幽冥血海_血河池.md":"DDjh7ifo","地图_幽冥血海_那刹.md":"CC1ghX8K","地图_幽冥血海_间忏.md":"Ca-C2Ny3","地图_弥天神域_index.md":"CQiGMFfg","地图_弥天神域_九佑.md":"Cq0rzsld","地图_弥天神域_永生.md":"o-LwvEpn","地图_弥天神域_湮灭.md":"BRqpR96X","地图_西牛贺洲_index.md":"LNvNzaTr","地图_西牛贺洲_不周山.md":"BypuDX8G","地图_西牛贺洲_摩多.md":"DeDJqTSS","地图_西牛贺洲_释罗.md":"bJMuJc5x","客户端.md":"BiWpXQXu","导航.md":"DZslm0Bq","角色_index.md":"ISwIjywL","角色_哪吒_1.md":"dhk0nNfp","角色_哪吒_2.md":"BgmRAVMI","角色_哪吒_index.md":"N8AO6C2w","角色_唐僧_1.md":"B0jsPqwJ","角色_唐僧_2.md":"BkQVF-FU","角色_唐僧_index.md":"DecJkOHV","角色_孙悟空_index.md":"r74AqaUW","角色_孙悟空_当前最强武器防具.md":"3ScTsFyb","角色_孙悟空_装备合成材料表.md":"BHniuWO6","角色_沙僧_1.md":"CLxun2_u","角色_沙僧_2.md":"D_TjIxfV","角色_沙僧_index.md":"Cz0gStAM","角色_猪八戒_1.md":"BIl6gINr","角色_猪八戒_2.md":"CVtI8Tf4","角色_猪八戒_index.md":"4aSY-eer","角色_玉兔_1.md":"BWJpFk0i","角色_玉兔_2.md":"cVFV3aQ1","角色_白龙_1.md":"BsjFtkZK","角色_白龙_2.md":"CQZRQU4X","角色_通用_index.md":"B8UVN_zn","角色_通用_丹药材料表.md":"DLFI9aTH","角色_通用_技能蓝耗表.md":"COWrGWTC","角色_通用_装备强化表.md":"D4fE6O83","角色_通用_角色属性解析.md":"B2UcF4oi","角色相关_index.md":"oZyQdjbD","角色相关_咒印_index.md":"CKNgsQ8W","角色相关_咒印_忿怒无障明王咒印.md":"FHsQGH0_","角色相关_咒印_曼陀罗华咒印.md":"BdokFNqD","角色相关_咒印_菩提慈悲咒印.md":"D0UImvoa","角色相关_四剑_index.md":"73p-sZaq","角色相关_四剑_剑意.md":"wPz7eGHh","角色相关_四剑_剑阵.md":"C05PsQJS","角色相关_宝石_index.md":"DB94x6Fw","角色相关_宝石_宝石.md":"DfSOWpGg","角色相关_宝石_易盘.md":"BkTqxKXM","角色相关_时装_1.md":"tB76GVHn","角色相关_时装_index.md":"BRGGlfms","角色相关_法宝_index.md":"DNN4cwBj","角色相关_法宝_地藏冥殿.md":"CibCjcA0","角色相关_法宝_实战法宝.md":"CQv1JPi0","角色相关_法宝_常用法宝.md":"DlVRAhz8","角色相关_法宝_罗汉堂.md":"BPyIs71F","角色相关_称号_index.md":"Df2Fpe6E","角色相关_称号_vip称号.md":"DJr3AfSD","角色相关_称号_万圣节.md":"RDSC0wTP","角色相关_称号_单身汪.md":"RWST9WJD","角色相关_称号_挑战之王.md":"DmPmldeO","角色相关_称号_联盟称号.md":"A_NWcbhY","角色相关_羽毛_index.md":"N7hQYAiG","角色相关_羽毛_羽毛.md":"-L7cEXBQ","角色相关_羽毛_翅膀.md":"C6LnUNNq","角色相关_饰品_index.md":"eaaVZl9l","角色相关_饰品_嗔恨煞戒.md":"CyZzL2p-","角色相关_饰品_常用饰品.md":"CgSfzDk2","角色相关_饰品_饰品战力表.md":"C8wtbL5W","角色相关_饰品_鱼纹.md":"DXW8G5lq","角色相关_魂器_index.md":"BEfwnPC-","角色相关_魂器_莲珠.md":"CvFHVrMS","角色相关_魂器_魂器.md":"BcYs74Tq","角色相关_魂器_魂石.md":"C33nlcM1"}
