{"index.md":"CIyqY--t","zmxy_index.md":"DamJcA8C","zmxy_单身汪.md":"HHdcCeG9","zmxy_忿怒无障明王咒印.md":"Bi8vyvu1","zmxy_时装.md":"M3THBN-a","咒印_index.md":"BQEHMWbZ","咒印_忿怒无障明王咒印.md":"bCssT4Yx","咒印_曼陀罗华咒印.md":"DlOT9btw","团队_index.md":"DVw7uvL1","地图_index.md":"CQqFLERt","地图_东胜神洲_index.md":"CfOEBFrS","地图_东胜神洲_云川.md":"ALDK6x7p","地图_东胜神洲_电.md":"Ci9oBPmh","地图_东胜神洲_雨.md":"DRx_kcLm","地图_东胜神洲_雷.md":"C8UPSCYN","地图_东胜神洲_风.md":"ya0me1e8","地图_北俱芦洲_index.md":"Mil344Mm","地图_北俱芦洲_天气.md":"CBfCW23C","地图_北俱芦洲_时间.md":"uYrYcYmH","地图_北俱芦洲_星域.md":"BaBGIyUY","地图_北俱芦洲_空间.md":"Cbrl_6tL","地图_南瞻部洲_index.md":"el3U8R6l","地图_南瞻部洲_冥海.md":"lBJy4-8b","地图_南瞻部洲_土.md":"b2dOuFDW","地图_南瞻部洲_木.md":"D2RXxJyE","地图_南瞻部洲_水.md":"5xzehalX","地图_南瞻部洲_火.md":"DnCJVSev","地图_南瞻部洲_金.md":"NPgeWvUq","地图_幽冥血海_index.md":"COAIySJI","地图_幽冥血海_伽岚.md":"DuxpniIX","地图_幽冥血海_无冥.md":"BE1vt-LD","地图_幽冥血海_洛湮.md":"BABs4D7T","地图_幽冥血海_血河池.md":"BTXKBZ2h","地图_幽冥血海_那刹.md":"C75T4BHL","地图_幽冥血海_间忏.md":"C4z3eErO","地图_弥天神域_index.md":"Djvcjqfx","地图_弥天神域_九佑.md":"DSYV2dde","地图_弥天神域_永生.md":"BCDMhc3Z","地图_弥天神域_湮灭.md":"CHpqlWCv","地图_西牛贺洲_index.md":"C4OV1EVw","地图_西牛贺洲_不周山.md":"DCLP0lLA","地图_西牛贺洲_摩多.md":"BTc6BX7m","地图_西牛贺洲_释罗.md":"gRddiY8f","导航.md":"DKGqsngK","游玩方式.md":"DQO2MMWQ","角色_index.md":"DEd9XYlB","角色_哪吒_1.md":"Ct05RM2i","角色_哪吒_2.md":"GVxviI25","角色_哪吒_index.md":"BzP7hwm3","角色_唐僧_1.md":"DHo_tDin","角色_唐僧_2.md":"Cd4M5UX4","角色_唐僧_index.md":"lTtX85GP","角色_孙悟空_index.md":"B8DjfaEt","角色_孙悟空_当前最强武器防具.md":"P6uDHQko","角色_孙悟空_装备合成材料表.md":"Jgd27Isu","角色_沙僧_1.md":"BmSPIJI4","角色_沙僧_2.md":"DVGTDhYI","角色_沙僧_index.md":"Dmejpb1N","角色_猪八戒_1.md":"B2vi8hVP","角色_猪八戒_2.md":"Bz0aYBrK","角色_猪八戒_index.md":"C4f02LX6","角色_玉兔_1.md":"DedT2bRJ","角色_玉兔_2.md":"CWCTz-u7","角色_白龙_1.md":"BH17UhYI","角色_白龙_2.md":"DT4mRlR_","角色_通用_index.md":"Cr0O_nUC","角色_通用_丹药材料表.md":"j54gSrhi","角色_通用_技能蓝耗表.md":"0bsJlCuL","角色_通用_装备强化表.md":"BNf5q_Fz","角色_通用_角色属性解析.md":"CVgnw86y","饰品_index.md":"BDpFFiH6","饰品_嗔恨煞戒.md":"C6diyohB","饰品_常见主线饰品.md":"Dp96Jpoj","饰品_稀有饰品.md":"B-kVxif9","饰品_饰品战力表.md":"Bb5yK1RS","饰品_鱼纹.md":"6hdr_ZF0","魂器_index.md":"Skx1KDLL","魂器_莲珠魂石.md":"Br9cWKm6","魂器_魂器.md":"Dk76NRXW"}
